{
	"category" : "RecognisingStructuralPatternsNotMain-StructureParsers",
	"classinstvars" : [
		 ],
	"classvars" : [
		 ],
	"commentStamp" : "Icewater 8/7/2016 10:52",
	"instvars" : [
		"ifSea1",
		"ifSea2",
		"if",
		"any",
		"ifStmt1",
		"eof",
		"space",
		"block",
		"ifStmt2",
		"noBracketsBlock",
		"ifSea3",
		"ifStmt3",
		"ifStmt4",
		"then",
		"ifSea4",
		"oneLineBlock",
		"blank",
		"newline",
		"roundBracketsBlock",
		"endif",
		"end",
		"ifElseStmt1",
		"elseBlock1",
		"else",
		"elseBlock2",
		"squareBracketsBlock",
		"ifElseStmt2",
		"ifElseSea2",
		"ifStmt5",
		"ifSea5" ],
	"name" : "IfOrIfElseParser",
	"pools" : [
		 ],
	"super" : "PPCompositeParser",
	"type" : "normal" }
